tinyscript/VERSION.txt
tinyscript/__conf__.py
tinyscript/__info__.py
tinyscript/__init__.py
tinyscript/__main__.py
tinyscript/argreparse.py
tinyscript/parser.py
tinyscript/template.py
tinyscript/features/__init__.py
tinyscript/features/handlers.py
tinyscript/features/hotkeys.py
tinyscript/features/interact.py
tinyscript/features/loglib.py
tinyscript/features/progress.py
tinyscript/features/step.py
tinyscript/features/timing.py
tinyscript/features/notify/__init__.py
tinyscript/features/notify/critical.png
tinyscript/features/notify/debug.png
tinyscript/features/notify/error.png
tinyscript/features/notify/failure.png
tinyscript/features/notify/info.png
tinyscript/features/notify/success.png
tinyscript/features/notify/warning.png
tinyscript/helpers/__init__.py
tinyscript/helpers/attack.py
tinyscript/helpers/classprop.py
tinyscript/helpers/common.py
tinyscript/helpers/compat.py
tinyscript/helpers/constants.py
tinyscript/helpers/decorators.py
tinyscript/helpers/dictionaries.py
tinyscript/helpers/docstring.py
tinyscript/helpers/expressions.py
tinyscript/helpers/fexec.py
tinyscript/helpers/inputs.py
tinyscript/helpers/layout.py
tinyscript/helpers/licenses.py
tinyscript/helpers/notify.py
tinyscript/helpers/parser.py
tinyscript/helpers/password.py
tinyscript/helpers/path.py
tinyscript/helpers/termsize.py
tinyscript/helpers/text.py
tinyscript/helpers/timeout.py
tinyscript/helpers/data/__init__.py
tinyscript/helpers/data/utils.py
tinyscript/helpers/data/transform/__init__.py
tinyscript/helpers/data/transform/common.py
tinyscript/helpers/data/transform/report.py
tinyscript/helpers/data/types/__init__.py
tinyscript/helpers/data/types/common.py
tinyscript/helpers/data/types/config.py
tinyscript/helpers/data/types/files.py
tinyscript/helpers/data/types/hash.py
tinyscript/helpers/data/types/network.py
tinyscript/helpers/data/types/strings.py
tinyscript/preimports/__init__.py
tinyscript/preimports/codep.py
tinyscript/preimports/ftools.py
tinyscript/preimports/hash.py
tinyscript-1.30.28.dist-info/licenses/LICENSE
tinyscript-1.30.28.dist-info/METADATA
tinyscript-1.30.28.dist-info/WHEEL
tinyscript-1.30.28.dist-info/entry_points.txt
tinyscript-1.30.28.dist-info/top_level.txt
tinyscript-1.30.28.dist-info/RECORD
