Metadata-Version: 2.4
Name: tinyscript
Version: 1.30.28
Summary: Devkit for quickly building CLI tools with Python
Author-email: Alexandre D'Hondt <alexandre.dhondt@gmail.com>
License:                     GNU GENERAL PUBLIC LICENSE
Project-URL: documentation, https://python-tinyscript.readthedocs.io/en/latest/?badge=latest
Project-URL: homepage, https://github.com/dhondta/python-tinyscript
Project-URL: issues, https://github.com/dhondta/python-tinyscript/issues
Project-URL: repository, https://github.com/dhondta/python-tinyscript
Keywords: python,development,programming,cli,devkit
Classifier: Development Status :: 5 - Production/Stable
Classifier: Environment :: Console
Classifier: Intended Audience :: Developers
Classifier: License :: OSI Approved :: GNU General Public License v3 or later (GPLv3+)
Classifier: Programming Language :: Python :: 3
Classifier: Topic :: Software Development :: Libraries :: Python Modules
Requires-Python: <4,>=3.8
License-File: LICENSE
Requires-Dist: argcomplete>=3.0.8
Requires-Dist: asciistuff>=1.3.3
Requires-Dist: codext>=1.15.7
Requires-Dist: coloredlogs
Requires-Dist: colorful
Requires-Dist: dateparser>=1.1.8
Requires-Dist: dicttoxml
Requires-Dist: fonttools>=4.43.0
Requires-Dist: ipaddress>=1.0.23
Requires-Dist: json2html
Requires-Dist: lazy_object_proxy>=1.9.0
Requires-Dist: markdown2>=2.5.4
Requires-Dist: netaddr
Requires-Dist: netifaces
Requires-Dist: packaging
Requires-Dist: patchy
Requires-Dist: pathlib2
Requires-Dist: pip>=24.0
Requires-Dist: plyer>=2.0.0
Requires-Dist: pydyf>=0.11.0
Requires-Dist: pygments>=2.8.1
Requires-Dist: pyminizip
Requires-Dist: pynput
Requires-Dist: pypandoc
Requires-Dist: pypiwin32; sys_platform == "windows"
Requires-Dist: python-magic
Requires-Dist: python-slugify
Requires-Dist: pyyaml>=5.3.1
Requires-Dist: requests>=2.32.2
Requires-Dist: rich
Requires-Dist: setuptools>=70.2.0
Requires-Dist: terminaltables
Requires-Dist: toml
Requires-Dist: tqdm
Requires-Dist: virtualenv>=20.26.3
Requires-Dist: weasyprint>=65.1
Requires-Dist: xmltodict
Dynamic: license-file
